{
  "protocol": "Lido",
  "position_id": "FllMeWithPositionId",
  "position_id_tech": "FillMeWithStETHOrWstETH",
  "position_id_human_readable": "FillMeWithPositionIdHumanReadable",
  "exec_config": [
    {
      "function_name": "exit_1",
      "label": "Unstake stETH",
      "test": true,
      "stresstest": false,
      "stresstest_error": "None",
      "description": "Unstake stETH for ETH",
      "parameters": []
    },
    {
      "function_name": "exit_2",
      "label": "Unstake wstETH",
      "test": true,
      "stresstest": false,
      "stresstest_error": "None",
      "description": "Unstake wstETH for ETH",
      "parameters": []
    },
    {
      "function_name": "exit_3",
      "label": "Swap stETH",
      "test": true,
      "stresstest": false,
      "stresstest_error": "None",
      "description": "Swap stETH for ETH",
      "parameters": [
        {
          "name": "max_slippage",
          "type": "input",
          "label": "Max slippage",
          "rules": {
            "min": 0.001,
            "max": 100
          }
        }
      ]
    },
    {
      "function_name": "exit_4",
      "label": "Swap wstETH",
      "test": true,
      "stresstest": false,
      "stresstest_error": "None",
      "description": "Swap wstETH for ETH",
      "parameters": [
        {
          "name": "max_slippage",
          "label": "Max slippage",
          "type": "input",
          "rules": {
            "min": 0.001,
            "max": 100
          }
        }
      ]
    }
  ]
}
